topsis/__init__.py
topsis/topsis.py
topsis_Pranav_102203059-1.2.dist-info/METADATA
topsis_Pranav_102203059-1.2.dist-info/WHEEL
topsis_Pranav_102203059-1.2.dist-info/entry_points.txt
topsis_Pranav_102203059-1.2.dist-info/top_level.txt
topsis_Pranav_102203059-1.2.dist-info/RECORD
