Metadata-Version: 2.1
Name: topsis_Pranav_102203059
Version: 1.2
Summary: A Python package to implement the TOPSIS method
Author: Pranav Jain
Author-email: pjain_be22@thapar.edu
Classifier: Development Status :: 4 - Beta
Classifier: Intended Audience :: Developers
Classifier: Programming Language :: Python :: 3
Classifier: Operating System :: OS Independent
Requires-Python: >=3.6
Requires-Dist: pandas
Requires-Dist: numpy
